README.md
setup.cfg
setup.py
PcnnLib/__init__.py
PcnnLib/utility.py
PcnnLib.egg-info/PKG-INFO
PcnnLib.egg-info/SOURCES.txt
PcnnLib.egg-info/dependency_links.txt
PcnnLib.egg-info/requires.txt
PcnnLib.egg-info/top_level.txt
PcnnLib/helpers/__init__.py
PcnnLib/helpers/file_helpers.py
PcnnLib/image_preprocessing/__init__.py
PcnnLib/image_preprocessing/directory_pipeline.py
PcnnLib/image_preprocessing/image_converters.py
PcnnLib/image_preprocessing/images_pipeline.py
PcnnLib/metrics/__init__.py
PcnnLib/metrics/mse.py
PcnnLib/metrics/time_signature.py
PcnnLib/network_lib/__init__.py
PcnnLib/network_lib/connection.py
PcnnLib/network_lib/network.py
PcnnLib/network_lib/statistic_record.py
PcnnLib/network_lib/neuron_factories/__init__.py
PcnnLib/network_lib/neuron_factories/full_neuron_factory.py
PcnnLib/network_lib/neuron_factories/simple_neuron_factory.py
PcnnLib/network_lib/neurons/__init__.py
PcnnLib/network_lib/neurons/full_neuron.py
PcnnLib/network_lib/neurons/simple_neuron.py
PcnnLib/tools/__init__.py
PcnnLib/tools/grid_search.py
PcnnLib/tools/spike_collector.py
tests/__init__.py
tests/image_converter_test.py
tests/network_linking_test.py
tests/neuron_test.py
tests/tools_test.py