Metadata-Version: 1.1
Name: PcnnLib
Version: 0.7
Summary: Pulse-coupled neural network library
Home-page: https://gitlab.com/trikster/pcnnlib
Author: Anton Zotov
Author-email: anton@zotov.online
License: MIT
Download-URL: https://gitlab.com/trikster/pcnnlib
Keywords: pcnn,pulse,neural,impulse
Platform: UNKNOWN
Classifier: Development Status :: 3 - Alpha
Classifier: Intended Audience :: Developers
Classifier: Topic :: Software Development :: Build Tools
Classifier: License :: OSI Approved :: MIT License
Classifier: Programming Language :: Python :: 3.6
Classifier: Programming Language :: Python :: 3.8
